ai_embedder/__init__.py
ai_embedder/__main__.py
ai_embedder/main.py
ai_embedder-1.0.2.dist-info/LICENSE
ai_embedder-1.0.2.dist-info/METADATA
ai_embedder-1.0.2.dist-info/WHEEL
ai_embedder-1.0.2.dist-info/top_level.txt
ai_embedder-1.0.2.dist-info/RECORD
